Workbook

Sheet Summary
A1: AI support agent: which customer queries to automate
A2: Fictional client: a digital bank's customer support desk. Data: Banking77 (10,003 real-style customer queries, 77 intents).
A4: Key numbers
A5: Customer queries analysed | B5: =Group_Summary!B16 -> 10003
A6: Intents | B6: =Group_Summary!H16 -> 77
A7: Bot can resolve outright (risk 1) | B7: =Group_Summary!D16/Group_Summary!B16 -> 0.48875337
A8: Bot triages, agent resolves (risk 2) | B8: =Group_Summary!E16/Group_Summary!B16 -> 0.36818954
A9: Must go straight to a human (risk 3) | B9: =Group_Summary!F16/Group_Summary!B16 -> 0.14305708
A10: Pilot: groups in scope | B10: =Group_Summary!B3 -> 4
A11: Pilot: queries the bot resolves | B11: =SUMIFS(Group_Summary!D6:D15,Group_Summary!J6:J15,"Pilot") -> 3620
A12: Pilot: share of all queries | B12: =SUMIFS(Group_Summary!D6:D15,Group_Summary!J6:J15,"Pilot")/Group_Summary!B16 -> 0.36189143
A14: Pilot groups (from Group_Summary) | C14: Bot-resolvable queries
A15: =IFERROR(INDEX(Group_Summary!$A$6:$A$15,MATCH(1,Group_Summary!$I$6:$I$15,0)),"") -> Card usage & features | B15: =IFERROR(INDEX(Group_Summary!$D$6:$D$15,MATCH(1,Group_Summary!$I$6:$I$15,0)),"") -> 1124
A16: =IFERROR(INDEX(Group_Summary!$A$6:$A$15,MATCH(2,Group_Summary!$I$6:$I$15,0)),"") -> Card delivery & activation | B16: =IFERROR(INDEX(Group_Summary!$D$6:$D$15,MATCH(2,Group_Summary!$I$6:$I$15,0)),"") -> 1047
A17: =IFERROR(INDEX(Group_Summary!$A$6:$A$15,MATCH(3,Group_Summary!$I$6:$I$15,0)),"") -> Fees & charges | B17: =IFERROR(INDEX(Group_Summary!$D$6:$D$15,MATCH(3,Group_Summary!$I$6:$I$15,0)),"") -> 882
A18: =IFERROR(INDEX(Group_Summary!$A$6:$A$15,MATCH(4,Group_Summary!$I$6:$I$15,0)),"") -> Top-ups | B18: =IFERROR(INDEX(Group_Summary!$D$6:$D$15,MATCH(4,Group_Summary!$I$6:$I$15,0)),"") -> 567
A20: Findings
A21: 1. | B21: About half of all queries are general policy questions (delivery times, fees, limits, how-to) that a knowledge-base bot can answer without touching a customer's account.
A22: 2. | B22: Card usage, card delivery, fees and top-ups hold the most bot-resolvable volume, so they form the pilot. All four are low-risk and policy-driven.
A23: 3. | B23: Transfers are the second-largest group but mostly need account details (pending/failed transfers), so the bot triages and hands off rather than resolving.
A24: 4. | B24: Fraud & security, refunds and cash disputes are excluded from automation entirely. A wrong answer there costs the customer money, so they go straight to a human.
A25: 5. | B25: Limitation: Banking77 is a research dataset, so volumes are a proxy. With a real client, the same SQL runs on their ticket logs and adds handle time and CSAT.
A27: Sheets: Group_Summary (pilot logic + chart) · Intent_Analysis (77 intents, editable risk) · Risk_Rules · Data_Quality · SQL · Raw_Data
A28: Blue cells are analyst inputs (risk levels, pilot size). Everything else is formula-driven.

Sheet Intent_Analysis
A1: Intent analysis: volume, risk and handling for all 77 intents
A2: Query counts are COUNTIF formulas on Raw_Data. Risk (blue) is an analyst judgement: edit it and every other sheet updates. See Risk_Rules for definitions.
A4: Intent | B4: Business group | C4: Queries | D4: % of total | E4: Risk (1-3) | F4: Handling | G4: In pilot scope?
A5: why_verify_identity | B5: Account & identity | C5: =COUNTIF(Raw_Data!$B$2:$B$10004,"why_verify_identity") -> 121 | D5: =C5/SUM($C$5:$C$81) -> 0.012096371 | E5: 1 | F5: =IF(E5=1,"Bot resolves",IF(E5=2,"Bot triages, agent resolves","Immediate human handoff")) -> Bot resolves | G5: =IF(AND(E5=1,INDEX(Group_Summary!$J$6:$J$15,MATCH(B5,Group_Summary!$A$6:$A$15,0))="Pilot"),"Yes","No") -> No
A6: edit_personal_details | B6: Account & identity | C6: =COUNTIF(Raw_Data!$B$2:$B$10004,"edit_personal_details") -> 121 | D6: =C6/SUM($C$5:$C$81) -> 0.012096371 | E6: 2 | F6: =IF(E6=1,"Bot resolves",IF(E6=2,"Bot triages, agent resolves","Immediate human handoff")) -> Bot triages, agent resolves | G6: =IF(AND(E6=1,INDEX(Group_Summary!$J$6:$J$15,MATCH(B6,Group_Summary!$A$6:$A$15,0))="Pilot"),"Yes","No") -> No
A7: verify_source_of_funds | B7: Account & identity | C7: =COUNTIF(Raw_Data!$B$2:$B$10004,"verify_source_of_funds") -> 113 | D7: =C7/SUM($C$5:$C$81) -> 0.011296611 | E7: 1 | F7: =IF(E7=1,"Bot resolves",IF(E7=2,"Bot triages, agent resolves","Immediate human handoff")) -> Bot resolves | G7: =IF(AND(E7=1,INDEX(Group_Summary!$J$6:$J$15,MATCH(B7,Group_Summary!$A$6:$A$15,0))="Pilot"),"Yes","No") -> No
A8: age_limit | B8: Account & identity | C8: =COUNTIF(Raw_Data!$B$2:$B$10004,"age_limit") -> 110 | D8: =C8/SUM($C$5:$C$81) -> 0.010996701 | E8: 1 | F8: =IF(E8=1,"Bot resolves",IF(E8=2,"Bot triages, agent resolves","Immediate human handoff")) -> Bot resolves | G8: =IF(AND(E8=1,INDEX(Group_Summary!$J$6:$J$15,MATCH(B8,Group_Summary!$A$6:$A$15,0))="Pilot"),"Yes","No") -> No
A9: terminate_account | B9: Account & identity | C9: =COUNTIF(Raw_Data!$B$2:$B$10004,"terminate_account") -> 108 | D9: =C9/SUM($C$5:$C$81) -> 0.010796761 | E9: 3 | F9: =IF(E9=1,"Bot resolves",IF(E9=2,"Bot triages, agent resolves","Immediate human handoff")) -> Immediate human handoff | G9: =IF(AND(E9=1,INDEX(Group_Summary!$J$6:$J$15,MATCH(B9,Group_Summary!$A$6:$A$15,0))="Pilot"),"Yes","No") -> No
A10: passcode_forgotten | B10: Account & identity | C10: =COUNTIF(Raw_Data!$B$2:$B$10004,"passcode_forgotten") -> 105 | D10: =C10/SUM($C$5:$C$81) -> 0.010496851 | E10: 2 | F10: =IF(E10=1,"Bot resolves",IF(E10=2,"Bot triages, agent resolves","Immediate human handoff")) -> Bot triages, agent resolves | G10: =IF(AND(E10=1,INDEX(Group_Summary!$J$6:$J$15,MATCH(B10,Group_Summary!$A$6:$A$15,0))="Pilot"),"Yes","No") -> No
A11: verify_my_identity | B11: Account & identity | C11: =COUNTIF(Raw_Data!$B$2:$B$10004,"verify_my_identity") -> 104 | D11: =C11/SUM($C$5:$C$81) -> 0.010396881 | E11: 1 | F11: =IF(E11=1,"Bot resolves",IF(E11=2,"Bot triages, agent resolves","Immediate human handoff")) -> Bot resolves | G11: =IF(AND(E11=1,INDEX(Group_Summary!$J$6:$J$15,MATCH(B11,Group_Summary!$A$6:$A$15,0))="Pilot"),"Yes","No") -> No
A12: unable_to_verify_identity | B12: Account & identity | C12: =COUNTIF(Raw_Data!$B$2:$B$10004,"unable_to_verify_identity") -> 102 | D12: =C12/SUM($C$5:$C$81) -> 0.010196941 | E12: 2 | F12: =IF(E12=1,"Bot resolves",IF(E12=2,"Bot triages, agent resolves","Immediate human handoff")) -> Bot triages, agent resolves | G12: =IF(AND(E12=1,INDEX(Group_Summary!$J$6:$J$15,MATCH(B12,Group_Summary!$A$6:$A$15,0))="Pilot"),"Yes","No") -> No
A13: activate_my_card | B13: Card delivery & activation | C13: =COUNTIF(Raw_Data!$B$2:$B$10004,"activate_my_card") -> 159 | D13: =C13/SUM($C$5:$C$81) -> 0.015895231 | E13: 1 | F13: =IF(E13=1,"Bot resolves",IF(E13=2,"Bot triages, agent resolves","Immediate human handoff")) -> Bot resolves | G13: =IF(AND(E13=1,INDEX(Group_Summary!$J$6:$J$15,MATCH(B13,Group_Summary!$A$6:$A$15,0))="Pilot"),"Yes","No") -> Yes
A14: card_arrival | B14: Card delivery & activation | C14: =COUNTIF(Raw_Data!$B$2:$B$10004,"card_arrival") -> 153 | D14: =C14/SUM($C$5:$C$81) -> 0.015295411 | E14: 1 | F14: =IF(E14=1,"Bot resolves",IF(E14=2,"Bot triages, agent resolves","Immediate human handoff")) -> Bot resolves | G14: =IF(AND(E14=1,INDEX(Group_Summary!$J$6:$J$15,MATCH(B14,Group_Summary!$A$6:$A$15,0))="Pilot"),"Yes","No") -> Yes
A15: card_linking | B15: Card delivery & activation | C15: =COUNTIF(Raw_Data!$B$2:$B$10004,"card_linking") -> 139 | D15: =C15/SUM($C$5:$C$81) -> 0.013895831 | E15: 1 | F15: =IF(E15=1,"Bot resolves",IF(E15=2,"Bot triages, agent resolves","Immediate human handoff")) -> Bot resolves | G15: =IF(AND(E15=1,INDEX(Group_Summary!$J$6:$J$15,MATCH(B15,Group_Summary!$A$6:$A$15,0))="Pilot"),"Yes","No") -> Yes
A16: getting_spare_card | B16: Card delivery & activation | C16: =COUNTIF(Raw_Data!$B$2:$B$10004,"getting_spare_card") -> 129 | D16: =C16/SUM($C$5:$C$81) -> 0.012896131 | E16: 1 | F16: =IF(E16=1,"Bot resolves",IF(E16=2,"Bot triages, agent resolves","Immediate human handoff")) -> Bot resolves | G16: =IF(AND(E16=1,INDEX(Group_Summary!$J$6:$J$15,MATCH(B16,Group_Summary!$A$6:$A$15,0))="Pilot"),"Yes","No") -> Yes
A17: card_about_to_expire | B17: Card delivery & activation | C17: =COUNTIF(Raw_Data!$B$2:$B$10004,"card_about_to_expire") -> 129 | D17: =C17/SUM($C$5:$C$81) -> 0.012896131 | E17: 1 | F17: =IF(E17=1,"Bot resolves",IF(E17=2,"Bot triages, agent resolves","Immediate human handoff")) -> Bot resolves | G17: =IF(AND(E17=1,INDEX(Group_Summary!$J$6:$J$15,MATCH(B17,Group_Summary!$A$6:$A$15,0))="Pilot"),"Yes","No") -> Yes
A18: order_physical_card | B18: Card delivery & activation | C18: =COUNTIF(Raw_Data!$B$2:$B$10004,"order_physical_card") -> 120 | D18: =C18/SUM($C$5:$C$81) -> 0.011996401 | E18: 1 | F18: =IF(E18=1,"Bot resolves",IF(E18=2,"Bot triages, agent resolves","Immediate human handoff")) -> Bot resolves | G18: =IF(AND(E18=1,INDEX(Group_Summary!$J$6:$J$15,MATCH(B18,Group_Summary!$A$6:$A$15,0))="Pilot"),"Yes","No") -> Yes
A19: card_delivery_estimate | B19: Card delivery & activation | C19: =COUNTIF(Raw_Data!$B$2:$B$10004,"card_delivery_estimate") -> 112 | D19: =C19/SUM($C$5:$C$81) -> 0.011196641 | E19: 1 | F19: =IF(E19=1,"Bot resolves",IF(E19=2,"Bot triages, agent resolves","Immediate human handoff")) -> Bot resolves | G19: =IF(AND(E19=1,INDEX(Group_Summary!$J$6:$J$15,MATCH(B19,Group_Summary!$A$6:$A$15,0))="Pilot"),"Yes","No") -> Yes
A20: get_physical_card | B20: Card delivery & activation | C20: =COUNTIF(Raw_Data!$B$2:$B$10004,"get_physical_card") -> 106 | D20: =C20/SUM($C$5:$C$81) -> 0.010596821 | E20: 1 | F20: =IF(E20=1,"Bot resolves",IF(E20=2,"Bot triages, agent resolves","Immediate human handoff")) -> Bot resolves | G20: =IF(AND(E20=1,INDEX(Group_Summary!$J$6:$J$15,MATCH(B20,Group_Summary!$A$6:$A$15,0))="Pilot"),"Yes","No") -> Yes
A21: transaction_charged_twice | B21: Card payments & refunds | C21: =COUNTIF(Raw_Data!$B$2:$B$10004,"transaction_charged_twice") -> 175 | D21: =C21/SUM($C$5:$C$81) -> 0.017494752 | E21: 3 | F21: =IF(E21=1,"Bot resolves",IF(E21=2,"Bot triages, agent resolves","Immediate human handoff")) -> Immediate human handoff | G21: =IF(AND(E21=1,INDEX(Group_Summary!$J$6:$J$15,MATCH(B21,Group_Summary!$A$6:$A$15,0))="Pilot"),"Yes","No") -> No
A22: request_refund | B22: Card payments & refunds | C22: =COUNTIF(Raw_Data!$B$2:$B$10004,"request_refund") -> 169 | D22: =C22/SUM($C$5:$C$81) -> 0.016894932 | E22: 3 | F22: =IF(E22=1,"Bot resolves",IF(E22=2,"Bot triages, agent resolves","Immediate human handoff")) -> Immediate human handoff | G22: =IF(AND(E22=1,INDEX(Group_Summary!$J$6:$J$15,MATCH(B22,Group_Summary!$A$6:$A$15,0))="Pilot"),"Yes","No") -> No
A23: Refund_not_showing_up | B23: Card payments & refunds | C23: =COUNTIF(Raw_Data!$B$2:$B$10004,"Refund_not_showing_up") -> 162 | D23: =C23/SUM($C$5:$C$81) -> 0.016195141 | E23: 2 | F23: =IF(E23=1,"Bot resolves",IF(E23=2,"Bot triages, agent resolves","Immediate human handoff")) -> Bot triages, agent resolves | G23: =IF(AND(E23=1,INDEX(Group_Summary!$J$6:$J$15,MATCH(B23,Group_Summary!$A$6:$A$15,0))="Pilot"),"Yes","No") -> No
A24: reverted_card_payment? | B24: Card payments & refunds | C24: =COUNTIF(Raw_Data!$B$2:$B$10004,"reverted_card_payment~?") -> 161 | D24: =C24/SUM($C$5:$C$81) -> 0.016095171 | E24: 2 | F24: =IF(E24=1,"Bot resolves",IF(E24=2,"Bot triages, agent resolves","Immediate human handoff")) -> Bot triages, agent resolves | G24: =IF(AND(E24=1,INDEX(Group_Summary!$J$6:$J$15,MATCH(B24,Group_Summary!$A$6:$A$15,0))="Pilot"),"Yes","No") -> No
A25: pending_card_payment | B25: Card payments & refunds | C25: =COUNTIF(Raw_Data!$B$2:$B$10004,"pending_card_payment") -> 159 | D25: =C25/SUM($C$5:$C$81) -> 0.015895231 | E25: 2 | F25: =IF(E25=1,"Bot resolves",IF(E25=2,"Bot triages, agent resolves","Immediate human handoff")) -> Bot triages, agent resolves | G25: =IF(AND(E25=1,INDEX(Group_Summary!$J$6:$J$15,MATCH(B25,Group_Summary!$A$6:$A$15,0))="Pilot"),"Yes","No") -> No
A26: declined_card_payment | B26: Card usage & features | C26: =COUNTIF(Raw_Data!$B$2:$B$10004,"declined_card_payment") -> 153 | D26: =C26/SUM($C$5:$C$81) -> 0.015295411 | E26: 2 | F26: =IF(E26=1,"Bot resolves",IF(E26=2,"Bot triages, agent resolves","Immediate human handoff")) -> Bot triages, agent resolves | G26: =IF(AND(E26=1,INDEX(Group_Summary!$J$6:$J$15,MATCH(B26,Group_Summary!$A$6:$A$15,0))="Pilot"),"Yes","No") -> No
A27: visa_or_mastercard | B27: Card usage & features | C27: =COUNTIF(Raw_Data!$B$2:$B$10004,"visa_or_mastercard") -> 135 | D27: =C27/SUM($C$5:$C$81) -> 0.013495951 | E27: 1 | F27: =IF(E27=1,"Bot resolves",IF(E27=2,"Bot triages, agent resolves","Immediate human handoff")) -> Bot resolves | G27: =IF(AND(E27=1,INDEX(Group_Summary!$J$6:$J$15,MATCH(B27,Group_Summary!$A$6:$A$15,0))="Pilot"),"Yes","No") -> Yes
A28: supported_cards_and_currencies | B28: Card usage & features | C28: =COUNTIF(Raw_Data!$B$2:$B$10004,"supported_cards_and_currencies") -> 129 | D28: =C28/SUM($C$5:$C$81) -> 0.012896131 | E28: 1 | F28: =IF(E28=1,"Bot resolves",IF(E28=2,"Bot triages, agent resolves","Immediate human handoff")) -> Bot resolves | G28: =IF(AND(E28=1,INDEX(Group_Summary!$J$6:$J$15,MATCH(B28,Group_Summary!$A$6:$A$15,0))="Pilot"),"Yes","No") -> Yes
A29: apple_pay_or_google_pay | B29: Card usage & features | C29: =COUNTIF(Raw_Data!$B$2:$B$10004,"apple_pay_or_google_pay") -> 126 | D29: =C29/SUM($C$5:$C$81) -> 0.012596221 | E29: 1 | F29: =IF(E29=1,"Bot resolves",IF(E29=2,"Bot triages, agent resolves","Immediate human handoff")) -> Bot resolves | G29: =IF(AND(E29=1,INDEX(Group_Summary!$J$6:$J$15,MATCH(B29,Group_Summary!$A$6:$A$15,0))="Pilot"),"Yes","No") -> Yes
A30: change_pin | B30: Card usage & features | C30: =COUNTIF(Raw_Data!$B$2:$B$10004,"change_pin") -> 122 | D30: =C30/SUM($C$5:$C$81) -> 0.012196341 | E30: 1 | F30: =IF(E30=1,"Bot resolves",IF(E30=2,"Bot triages, agent resolves","Immediate human handoff")) -> Bot resolves | G30: =IF(AND(E30=1,INDEX(Group_Summary!$J$6:$J$15,MATCH(B30,Group_Summary!$A$6:$A$15,0))="Pilot"),"Yes","No") -> Yes
A31: disposable_card_limits | B31: Card usage & features | C31: =COUNTIF(Raw_Data!$B$2:$B$10004,"disposable_card_limits") -> 121 | D31: =C31/SUM($C$5:$C$81) -> 0.012096371 | E31: 1 | F31: =IF(E31=1,"Bot resolves",IF(E31=2,"Bot triages, agent resolves","Immediate human handoff")) -> Bot resolves | G31: =IF(AND(E31=1,INDEX(Group_Summary!$J$6:$J$15,MATCH(B31,Group_Summary!$A$6:$A$15,0))="Pilot"),"Yes","No") -> Yes
A32: pin_blocked | B32: Card usage & features | C32: =COUNTIF(Raw_Data!$B$2:$B$10004,"pin_blocked") -> 115 | D32: =C32/SUM($C$5:$C$81) -> 0.011496551 | E32: 1 | F32: =IF(E32=1,"Bot resolves",IF(E32=2,"Bot triages, agent resolves","Immediate human handoff")) -> Bot resolves | G32: =IF(AND(E32=1,INDEX(Group_Summary!$J$6:$J$15,MATCH(B32,Group_Summary!$A$6:$A$15,0))="Pilot"),"Yes","No") -> Yes
A33: card_not_working | B33: Card usage & features | C33: =COUNTIF(Raw_Data!$B$2:$B$10004,"card_not_working") -> 112 | D33: =C33/SUM($C$5:$C$81) -> 0.011196641 | E33: 2 | F33: =IF(E33=1,"Bot resolves",IF(E33=2,"Bot triages, agent resolves","Immediate human handoff")) -> Bot triages, agent resolves | G33: =IF(AND(E33=1,INDEX(Group_Summary!$J$6:$J$15,MATCH(B33,Group_Summary!$A$6:$A$15,0))="Pilot"),"Yes","No") -> No
A34: getting_virtual_card | B34: Card usage & features | C34: =COUNTIF(Raw_Data!$B$2:$B$10004,"getting_virtual_card") -> 98 | D34: =C34/SUM($C$5:$C$81) -> 0.0097970609 | E34: 1 | F34: =IF(E34=1,"Bot resolves",IF(E34=2,"Bot triages, agent resolves","Immediate human handoff")) -> Bot resolves | G34: =IF(AND(E34=1,INDEX(Group_Summary!$J$6:$J$15,MATCH(B34,Group_Summary!$A$6:$A$15,0))="Pilot"),"Yes","No") -> Yes
A35: get_disposable_virtual_card | B35: Card usage & features | C35: =COUNTIF(Raw_Data!$B$2:$B$10004,"get_disposable_virtual_card") -> 97 | D35: =C35/SUM($C$5:$C$81) -> 0.0096970909 | E35: 1 | F35: =IF(E35=1,"Bot resolves",IF(E35=2,"Bot triages, agent resolves","Immediate human handoff")) -> Bot resolves | G35: =IF(AND(E35=1,INDEX(Group_Summary!$J$6:$J$15,MATCH(B35,Group_Summary!$A$6:$A$15,0))="Pilot"),"Yes","No") -> Yes
A36: atm_support | B36: Card usage & features | C36: =COUNTIF(Raw_Data!$B$2:$B$10004,"atm_support") -> 87 | D36: =C36/SUM($C$5:$C$81) -> 0.0086973908 | E36: 1 | F36: =IF(E36=1,"Bot resolves",IF(E36=2,"Bot triages, agent resolves","Immediate human handoff")) -> Bot resolves | G36: =IF(AND(E36=1,INDEX(Group_Summary!$J$6:$J$15,MATCH(B36,Group_Summary!$A$6:$A$15,0))="Pilot"),"Yes","No") -> Yes
A37: card_swallowed | B37: Card usage & features | C37: =COUNTIF(Raw_Data!$B$2:$B$10004,"card_swallowed") -> 61 | D37: =C37/SUM($C$5:$C$81) -> 0.0060981705 | E37: 2 | F37: =IF(E37=1,"Bot resolves",IF(E37=2,"Bot triages, agent resolves","Immediate human handoff")) -> Bot triages, agent resolves | G37: =IF(AND(E37=1,INDEX(Group_Summary!$J$6:$J$15,MATCH(B37,Group_Summary!$A$6:$A$15,0))="Pilot"),"Yes","No") -> No
A38: card_acceptance | B38: Card usage & features | C38: =COUNTIF(Raw_Data!$B$2:$B$10004,"card_acceptance") -> 59 | D38: =C38/SUM($C$5:$C$81) -> 0.0058982305 | E38: 1 | F38: =IF(E38=1,"Bot resolves",IF(E38=2,"Bot triages, agent resolves","Immediate human handoff")) -> Bot resolves | G38: =IF(AND(E38=1,INDEX(Group_Summary!$J$6:$J$15,MATCH(B38,Group_Summary!$A$6:$A$15,0))="Pilot"),"Yes","No") -> Yes
A39: virtual_card_not_working | B39: Card usage & features | C39: =COUNTIF(Raw_Data!$B$2:$B$10004,"virtual_card_not_working") -> 41 | D39: =C39/SUM($C$5:$C$81) -> 0.0040987704 | E39: 2 | F39: =IF(E39=1,"Bot resolves",IF(E39=2,"Bot triages, agent resolves","Immediate human handoff")) -> Bot triages, agent resolves | G39: =IF(AND(E39=1,INDEX(Group_Summary!$J$6:$J$15,MATCH(B39,Group_Summary!$A$6:$A$15,0))="Pilot"),"Yes","No") -> No
A40: contactless_not_working | B40: Card usage & features | C40: =COUNTIF(Raw_Data!$B$2:$B$10004,"contactless_not_working") -> 35 | D40: =C40/SUM($C$5:$C$81) -> 0.0034989503 | E40: 1 | F40: =IF(E40=1,"Bot resolves",IF(E40=2,"Bot triages, agent resolves","Immediate human handoff")) -> Bot resolves | G40: =IF(AND(E40=1,INDEX(Group_Summary!$J$6:$J$15,MATCH(B40,Group_Summary!$A$6:$A$15,0))="Pilot"),"Yes","No") -> Yes
A41: balance_not_updated_after_cheque_or_cash_deposit | B41: Cash, ATM & deposits | C41: =COUNTIF(Raw_Data!$B$2:$B$10004,"balance_not_updated_after_cheque_or_cash_deposit") -> 181 | D41: =C41/SUM($C$5:$C$81) -> 0.018094572 | E41: 2 | F41: =IF(E41=1,"Bot resolves",IF(E41=2,"Bot triages, agent resolves","Immediate human handoff")) -> Bot triages, agent resolves | G41: =IF(AND(E41=1,INDEX(Group_Summary!$J$6:$J$15,MATCH(B41,Group_Summary!$A$6:$A$15,0))="Pilot"),"Yes","No") -> No
A42: wrong_amount_of_cash_received | B42: Cash, ATM & deposits | C42: =COUNTIF(Raw_Data!$B$2:$B$10004,"wrong_amount_of_cash_received") -> 180 | D42: =C42/SUM($C$5:$C$81) -> 0.017994602 | E42: 3 | F42: =IF(E42=1,"Bot resolves",IF(E42=2,"Bot triages, agent resolves","Immediate human handoff")) -> Immediate human handoff | G42: =IF(AND(E42=1,INDEX(Group_Summary!$J$6:$J$15,MATCH(B42,Group_Summary!$A$6:$A$15,0))="Pilot"),"Yes","No") -> No
A43: declined_cash_withdrawal | B43: Cash, ATM & deposits | C43: =COUNTIF(Raw_Data!$B$2:$B$10004,"declined_cash_withdrawal") -> 173 | D43: =C43/SUM($C$5:$C$81) -> 0.017294812 | E43: 2 | F43: =IF(E43=1,"Bot resolves",IF(E43=2,"Bot triages, agent resolves","Immediate human handoff")) -> Bot triages, agent resolves | G43: =IF(AND(E43=1,INDEX(Group_Summary!$J$6:$J$15,MATCH(B43,Group_Summary!$A$6:$A$15,0))="Pilot"),"Yes","No") -> No
A44: pending_cash_withdrawal | B44: Cash, ATM & deposits | C44: =COUNTIF(Raw_Data!$B$2:$B$10004,"pending_cash_withdrawal") -> 143 | D44: =C44/SUM($C$5:$C$81) -> 0.014295711 | E44: 2 | F44: =IF(E44=1,"Bot resolves",IF(E44=2,"Bot triages, agent resolves","Immediate human handoff")) -> Bot triages, agent resolves | G44: =IF(AND(E44=1,INDEX(Group_Summary!$J$6:$J$15,MATCH(B44,Group_Summary!$A$6:$A$15,0))="Pilot"),"Yes","No") -> No
A45: card_payment_wrong_exchange_rate | B45: Exchange rates & currencies | C45: =COUNTIF(Raw_Data!$B$2:$B$10004,"card_payment_wrong_exchange_rate") -> 167 | D45: =C45/SUM($C$5:$C$81) -> 0.016694992 | E45: 2 | F45: =IF(E45=1,"Bot resolves",IF(E45=2,"Bot triages, agent resolves","Immediate human handoff")) -> Bot triages, agent resolves | G45: =IF(AND(E45=1,INDEX(Group_Summary!$J$6:$J$15,MATCH(B45,Group_Summary!$A$6:$A$15,0))="Pilot"),"Yes","No") -> No
A46: wrong_exchange_rate_for_cash_withdrawal | B46: Exchange rates & currencies | C46: =COUNTIF(Raw_Data!$B$2:$B$10004,"wrong_exchange_rate_for_cash_withdrawal") -> 163 | D46: =C46/SUM($C$5:$C$81) -> 0.016295111 | E46: 2 | F46: =IF(E46=1,"Bot resolves",IF(E46=2,"Bot triages, agent resolves","Immediate human handoff")) -> Bot triages, agent resolves | G46: =IF(AND(E46=1,INDEX(Group_Summary!$J$6:$J$15,MATCH(B46,Group_Summary!$A$6:$A$15,0))="Pilot"),"Yes","No") -> No
A47: country_support | B47: Exchange rates & currencies | C47: =COUNTIF(Raw_Data!$B$2:$B$10004,"country_support") -> 129 | D47: =C47/SUM($C$5:$C$81) -> 0.012896131 | E47: 1 | F47: =IF(E47=1,"Bot resolves",IF(E47=2,"Bot triages, agent resolves","Immediate human handoff")) -> Bot resolves | G47: =IF(AND(E47=1,INDEX(Group_Summary!$J$6:$J$15,MATCH(B47,Group_Summary!$A$6:$A$15,0))="Pilot"),"Yes","No") -> No
A48: fiat_currency_support | B48: Exchange rates & currencies | C48: =COUNTIF(Raw_Data!$B$2:$B$10004,"fiat_currency_support") -> 126 | D48: =C48/SUM($C$5:$C$81) -> 0.012596221 | E48: 1 | F48: =IF(E48=1,"Bot resolves",IF(E48=2,"Bot triages, agent resolves","Immediate human handoff")) -> Bot resolves | G48: =IF(AND(E48=1,INDEX(Group_Summary!$J$6:$J$15,MATCH(B48,Group_Summary!$A$6:$A$15,0))="Pilot"),"Yes","No") -> No
A49: exchange_via_app | B49: Exchange rates & currencies | C49: =COUNTIF(Raw_Data!$B$2:$B$10004,"exchange_via_app") -> 118 | D49: =C49/SUM($C$5:$C$81) -> 0.011796461 | E49: 1 | F49: =IF(E49=1,"Bot resolves",IF(E49=2,"Bot triages, agent resolves","Immediate human handoff")) -> Bot resolves | G49: =IF(AND(E49=1,INDEX(Group_Summary!$J$6:$J$15,MATCH(B49,Group_Summary!$A$6:$A$15,0))="Pilot"),"Yes","No") -> No
A50: exchange_rate | B50: Exchange rates & currencies | C50: =COUNTIF(Raw_Data!$B$2:$B$10004,"exchange_rate") -> 112 | D50: =C50/SUM($C$5:$C$81) -> 0.011196641 | E50: 1 | F50: =IF(E50=1,"Bot resolves",IF(E50=2,"Bot triages, agent resolves","Immediate human handoff")) -> Bot resolves | G50: =IF(AND(E50=1,INDEX(Group_Summary!$J$6:$J$15,MATCH(B50,Group_Summary!$A$6:$A$15,0))="Pilot"),"Yes","No") -> No
A51: card_payment_fee_charged | B51: Fees & charges | C51: =COUNTIF(Raw_Data!$B$2:$B$10004,"card_payment_fee_charged") -> 187 | D51: =C51/SUM($C$5:$C$81) -> 0.018694392 | E51: 1 | F51: =IF(E51=1,"Bot resolves",IF(E51=2,"Bot triages, agent resolves","Immediate human handoff")) -> Bot resolves | G51: =IF(AND(E51=1,INDEX(Group_Summary!$J$6:$J$15,MATCH(B51,Group_Summary!$A$6:$A$15,0))="Pilot"),"Yes","No") -> Yes
A52: cash_withdrawal_charge | B52: Fees & charges | C52: =COUNTIF(Raw_Data!$B$2:$B$10004,"cash_withdrawal_charge") -> 177 | D52: =C52/SUM($C$5:$C$81) -> 0.017694692 | E52: 1 | F52: =IF(E52=1,"Bot resolves",IF(E52=2,"Bot triages, agent resolves","Immediate human handoff")) -> Bot resolves | G52: =IF(AND(E52=1,INDEX(Group_Summary!$J$6:$J$15,MATCH(B52,Group_Summary!$A$6:$A$15,0))="Pilot"),"Yes","No") -> Yes
A53: transfer_fee_charged | B53: Fees & charges | C53: =COUNTIF(Raw_Data!$B$2:$B$10004,"transfer_fee_charged") -> 172 | D53: =C53/SUM($C$5:$C$81) -> 0.017194842 | E53: 1 | F53: =IF(E53=1,"Bot resolves",IF(E53=2,"Bot triages, agent resolves","Immediate human handoff")) -> Bot resolves | G53: =IF(AND(E53=1,INDEX(Group_Summary!$J$6:$J$15,MATCH(B53,Group_Summary!$A$6:$A$15,0))="Pilot"),"Yes","No") -> Yes
A54: extra_charge_on_statement | B54: Fees & charges | C54: =COUNTIF(Raw_Data!$B$2:$B$10004,"extra_charge_on_statement") -> 166 | D54: =C54/SUM($C$5:$C$81) -> 0.016595021 | E54: 2 | F54: =IF(E54=1,"Bot resolves",IF(E54=2,"Bot triages, agent resolves","Immediate human handoff")) -> Bot triages, agent resolves | G54: =IF(AND(E54=1,INDEX(Group_Summary!$J$6:$J$15,MATCH(B54,Group_Summary!$A$6:$A$15,0))="Pilot"),"Yes","No") -> No
A55: exchange_charge | B55: Fees & charges | C55: =COUNTIF(Raw_Data!$B$2:$B$10004,"exchange_charge") -> 121 | D55: =C55/SUM($C$5:$C$81) -> 0.012096371 | E55: 1 | F55: =IF(E55=1,"Bot resolves",IF(E55=2,"Bot triages, agent resolves","Immediate human handoff")) -> Bot resolves | G55: =IF(AND(E55=1,INDEX(Group_Summary!$J$6:$J$15,MATCH(B55,Group_Summary!$A$6:$A$15,0))="Pilot"),"Yes","No") -> Yes
A56: top_up_by_card_charge | B56: Fees & charges | C56: =COUNTIF(Raw_Data!$B$2:$B$10004,"top_up_by_card_charge") -> 114 | D56: =C56/SUM($C$5:$C$81) -> 0.011396581 | E56: 1 | F56: =IF(E56=1,"Bot resolves",IF(E56=2,"Bot triages, agent resolves","Immediate human handoff")) -> Bot resolves | G56: =IF(AND(E56=1,INDEX(Group_Summary!$J$6:$J$15,MATCH(B56,Group_Summary!$A$6:$A$15,0))="Pilot"),"Yes","No") -> Yes
A57: top_up_by_bank_transfer_charge | B57: Fees & charges | C57: =COUNTIF(Raw_Data!$B$2:$B$10004,"top_up_by_bank_transfer_charge") -> 111 | D57: =C57/SUM($C$5:$C$81) -> 0.011096671 | E57: 1 | F57: =IF(E57=1,"Bot resolves",IF(E57=2,"Bot triages, agent resolves","Immediate human handoff")) -> Bot resolves | G57: =IF(AND(E57=1,INDEX(Group_Summary!$J$6:$J$15,MATCH(B57,Group_Summary!$A$6:$A$15,0))="Pilot"),"Yes","No") -> Yes
A58: direct_debit_payment_not_recognised | B58: Fraud & security | C58: =COUNTIF(Raw_Data!$B$2:$B$10004,"direct_debit_payment_not_recognised") -> 182 | D58: =C58/SUM($C$5:$C$81) -> 0.018194542 | E58: 3 | F58: =IF(E58=1,"Bot resolves",IF(E58=2,"Bot triages, agent resolves","Immediate human handoff")) -> Immediate human handoff | G58: =IF(AND(E58=1,INDEX(Group_Summary!$J$6:$J$15,MATCH(B58,Group_Summary!$A$6:$A$15,0))="Pilot"),"Yes","No") -> No
A59: card_payment_not_recognised | B59: Fraud & security | C59: =COUNTIF(Raw_Data!$B$2:$B$10004,"card_payment_not_recognised") -> 168 | D59: =C59/SUM($C$5:$C$81) -> 0.016794962 | E59: 3 | F59: =IF(E59=1,"Bot resolves",IF(E59=2,"Bot triages, agent resolves","Immediate human handoff")) -> Immediate human handoff | G59: =IF(AND(E59=1,INDEX(Group_Summary!$J$6:$J$15,MATCH(B59,Group_Summary!$A$6:$A$15,0))="Pilot"),"Yes","No") -> No
A60: cash_withdrawal_not_recognised | B60: Fraud & security | C60: =COUNTIF(Raw_Data!$B$2:$B$10004,"cash_withdrawal_not_recognised") -> 160 | D60: =C60/SUM($C$5:$C$81) -> 0.015995201 | E60: 3 | F60: =IF(E60=1,"Bot resolves",IF(E60=2,"Bot triages, agent resolves","Immediate human handoff")) -> Immediate human handoff | G60: =IF(AND(E60=1,INDEX(Group_Summary!$J$6:$J$15,MATCH(B60,Group_Summary!$A$6:$A$15,0))="Pilot"),"Yes","No") -> No
A61: lost_or_stolen_phone | B61: Fraud & security | C61: =COUNTIF(Raw_Data!$B$2:$B$10004,"lost_or_stolen_phone") -> 121 | D61: =C61/SUM($C$5:$C$81) -> 0.012096371 | E61: 3 | F61: =IF(E61=1,"Bot resolves",IF(E61=2,"Bot triages, agent resolves","Immediate human handoff")) -> Immediate human handoff | G61: =IF(AND(E61=1,INDEX(Group_Summary!$J$6:$J$15,MATCH(B61,Group_Summary!$A$6:$A$15,0))="Pilot"),"Yes","No") -> No
A62: compromised_card | B62: Fraud & security | C62: =COUNTIF(Raw_Data!$B$2:$B$10004,"compromised_card") -> 86 | D62: =C62/SUM($C$5:$C$81) -> 0.0085974208 | E62: 3 | F62: =IF(E62=1,"Bot resolves",IF(E62=2,"Bot triages, agent resolves","Immediate human handoff")) -> Immediate human handoff | G62: =IF(AND(E62=1,INDEX(Group_Summary!$J$6:$J$15,MATCH(B62,Group_Summary!$A$6:$A$15,0))="Pilot"),"Yes","No") -> No
A63: lost_or_stolen_card | B63: Fraud & security | C63: =COUNTIF(Raw_Data!$B$2:$B$10004,"lost_or_stolen_card") -> 82 | D63: =C63/SUM($C$5:$C$81) -> 0.0081975407 | E63: 3 | F63: =IF(E63=1,"Bot resolves",IF(E63=2,"Bot triages, agent resolves","Immediate human handoff")) -> Immediate human handoff | G63: =IF(AND(E63=1,INDEX(Group_Summary!$J$6:$J$15,MATCH(B63,Group_Summary!$A$6:$A$15,0))="Pilot"),"Yes","No") -> No
A64: pending_top_up | B64: Top-ups | C64: =COUNTIF(Raw_Data!$B$2:$B$10004,"pending_top_up") -> 149 | D64: =C64/SUM($C$5:$C$81) -> 0.014895531 | E64: 2 | F64: =IF(E64=1,"Bot resolves",IF(E64=2,"Bot triages, agent resolves","Immediate human handoff")) -> Bot triages, agent resolves | G64: =IF(AND(E64=1,INDEX(Group_Summary!$J$6:$J$15,MATCH(B64,Group_Summary!$A$6:$A$15,0))="Pilot"),"Yes","No") -> No
A65: top_up_reverted | B65: Top-ups | C65: =COUNTIF(Raw_Data!$B$2:$B$10004,"top_up_reverted") -> 146 | D65: =C65/SUM($C$5:$C$81) -> 0.014595621 | E65: 2 | F65: =IF(E65=1,"Bot resolves",IF(E65=2,"Bot triages, agent resolves","Immediate human handoff")) -> Bot triages, agent resolves | G65: =IF(AND(E65=1,INDEX(Group_Summary!$J$6:$J$15,MATCH(B65,Group_Summary!$A$6:$A$15,0))="Pilot"),"Yes","No") -> No
A66: top_up_failed | B66: Top-ups | C66: =COUNTIF(Raw_Data!$B$2:$B$10004,"top_up_failed") -> 145 | D66: =C66/SUM($C$5:$C$81) -> 0.014495651 | E66: 2 | F66: =IF(E66=1,"Bot resolves",IF(E66=2,"Bot triages, agent resolves","Immediate human handoff")) -> Bot triages, agent resolves | G66: =IF(AND(E66=1,INDEX(Group_Summary!$J$6:$J$15,MATCH(B66,Group_Summary!$A$6:$A$15,0))="Pilot"),"Yes","No") -> No
A67: automatic_top_up | B67: Top-ups | C67: =COUNTIF(Raw_Data!$B$2:$B$10004,"automatic_top_up") -> 127 | D67: =C67/SUM($C$5:$C$81) -> 0.012696191 | E67: 1 | F67: =IF(E67=1,"Bot resolves",IF(E67=2,"Bot triages, agent resolves","Immediate human handoff")) -> Bot resolves | G67: =IF(AND(E67=1,INDEX(Group_Summary!$J$6:$J$15,MATCH(B67,Group_Summary!$A$6:$A$15,0))="Pilot"),"Yes","No") -> Yes
A68: verify_top_up | B68: Top-ups | C68: =COUNTIF(Raw_Data!$B$2:$B$10004,"verify_top_up") -> 126 | D68: =C68/SUM($C$5:$C$81) -> 0.012596221 | E68: 1 | F68: =IF(E68=1,"Bot resolves",IF(E68=2,"Bot triages, agent resolves","Immediate human handoff")) -> Bot resolves | G68: =IF(AND(E68=1,INDEX(Group_Summary!$J$6:$J$15,MATCH(B68,Group_Summary!$A$6:$A$15,0))="Pilot"),"Yes","No") -> Yes
A69: top_up_by_cash_or_cheque | B69: Top-ups | C69: =COUNTIF(Raw_Data!$B$2:$B$10004,"top_up_by_cash_or_cheque") -> 114 | D69: =C69/SUM($C$5:$C$81) -> 0.011396581 | E69: 1 | F69: =IF(E69=1,"Bot resolves",IF(E69=2,"Bot triages, agent resolves","Immediate human handoff")) -> Bot resolves | G69: =IF(AND(E69=1,INDEX(Group_Summary!$J$6:$J$15,MATCH(B69,Group_Summary!$A$6:$A$15,0))="Pilot"),"Yes","No") -> Yes
A70: topping_up_by_card | B70: Top-ups | C70: =COUNTIF(Raw_Data!$B$2:$B$10004,"topping_up_by_card") -> 103 | D70: =C70/SUM($C$5:$C$81) -> 0.010296911 | E70: 1 | F70: =IF(E70=1,"Bot resolves",IF(E70=2,"Bot triages, agent resolves","Immediate human handoff")) -> Bot resolves | G70: =IF(AND(E70=1,INDEX(Group_Summary!$J$6:$J$15,MATCH(B70,Group_Summary!$A$6:$A$15,0))="Pilot"),"Yes","No") -> Yes
A71: top_up_limits | B71: Top-ups | C71: =COUNTIF(Raw_Data!$B$2:$B$10004,"top_up_limits") -> 97 | D71: =C71/SUM($C$5:$C$81) -> 0.0096970909 | E71: 1 | F71: =IF(E71=1,"Bot resolves",IF(E71=2,"Bot triages, agent resolves","Immediate human handoff")) -> Bot resolves | G71: =IF(AND(E71=1,INDEX(Group_Summary!$J$6:$J$15,MATCH(B71,Group_Summary!$A$6:$A$15,0))="Pilot"),"Yes","No") -> Yes
A72: transfer_not_received_by_recipient | B72: Transfers | C72: =COUNTIF(Raw_Data!$B$2:$B$10004,"transfer_not_received_by_recipient") -> 171 | D72: =C72/SUM($C$5:$C$81) -> 0.017094872 | E72: 2 | F72: =IF(E72=1,"Bot resolves",IF(E72=2,"Bot triages, agent resolves","Immediate human handoff")) -> Bot triages, agent resolves | G72: =IF(AND(E72=1,INDEX(Group_Summary!$J$6:$J$15,MATCH(B72,Group_Summary!$A$6:$A$15,0))="Pilot"),"Yes","No") -> No
A73: balance_not_updated_after_bank_transfer | B73: Transfers | C73: =COUNTIF(Raw_Data!$B$2:$B$10004,"balance_not_updated_after_bank_transfer") -> 171 | D73: =C73/SUM($C$5:$C$81) -> 0.017094872 | E73: 2 | F73: =IF(E73=1,"Bot resolves",IF(E73=2,"Bot triages, agent resolves","Immediate human handoff")) -> Bot triages, agent resolves | G73: =IF(AND(E73=1,INDEX(Group_Summary!$J$6:$J$15,MATCH(B73,Group_Summary!$A$6:$A$15,0))="Pilot"),"Yes","No") -> No
A74: cancel_transfer | B74: Transfers | C74: =COUNTIF(Raw_Data!$B$2:$B$10004,"cancel_transfer") -> 157 | D74: =C74/SUM($C$5:$C$81) -> 0.015695291 | E74: 2 | F74: =IF(E74=1,"Bot resolves",IF(E74=2,"Bot triages, agent resolves","Immediate human handoff")) -> Bot triages, agent resolves | G74: =IF(AND(E74=1,INDEX(Group_Summary!$J$6:$J$15,MATCH(B74,Group_Summary!$A$6:$A$15,0))="Pilot"),"Yes","No") -> No
A75: beneficiary_not_allowed | B75: Transfers | C75: =COUNTIF(Raw_Data!$B$2:$B$10004,"beneficiary_not_allowed") -> 156 | D75: =C75/SUM($C$5:$C$81) -> 0.015595321 | E75: 2 | F75: =IF(E75=1,"Bot resolves",IF(E75=2,"Bot triages, agent resolves","Immediate human handoff")) -> Bot triages, agent resolves | G75: =IF(AND(E75=1,INDEX(Group_Summary!$J$6:$J$15,MATCH(B75,Group_Summary!$A$6:$A$15,0))="Pilot"),"Yes","No") -> No
A76: pending_transfer | B76: Transfers | C76: =COUNTIF(Raw_Data!$B$2:$B$10004,"pending_transfer") -> 148 | D76: =C76/SUM($C$5:$C$81) -> 0.014795561 | E76: 2 | F76: =IF(E76=1,"Bot resolves",IF(E76=2,"Bot triages, agent resolves","Immediate human handoff")) -> Bot triages, agent resolves | G76: =IF(AND(E76=1,INDEX(Group_Summary!$J$6:$J$15,MATCH(B76,Group_Summary!$A$6:$A$15,0))="Pilot"),"Yes","No") -> No
A77: failed_transfer | B77: Transfers | C77: =COUNTIF(Raw_Data!$B$2:$B$10004,"failed_transfer") -> 137 | D77: =C77/SUM($C$5:$C$81) -> 0.013695891 | E77: 2 | F77: =IF(E77=1,"Bot resolves",IF(E77=2,"Bot triages, agent resolves","Immediate human handoff")) -> Bot triages, agent resolves | G77: =IF(AND(E77=1,INDEX(Group_Summary!$J$6:$J$15,MATCH(B77,Group_Summary!$A$6:$A$15,0))="Pilot"),"Yes","No") -> No
A78: declined_transfer | B78: Transfers | C78: =COUNTIF(Raw_Data!$B$2:$B$10004,"declined_transfer") -> 133 | D78: =C78/SUM($C$5:$C$81) -> 0.013296011 | E78: 2 | F78: =IF(E78=1,"Bot resolves",IF(E78=2,"Bot triages, agent resolves","Immediate human handoff")) -> Bot triages, agent resolves | G78: =IF(AND(E78=1,INDEX(Group_Summary!$J$6:$J$15,MATCH(B78,Group_Summary!$A$6:$A$15,0))="Pilot"),"Yes","No") -> No
A79: transfer_timing | B79: Transfers | C79: =COUNTIF(Raw_Data!$B$2:$B$10004,"transfer_timing") -> 128 | D79: =C79/SUM($C$5:$C$81) -> 0.012796161 | E79: 1 | F79: =IF(E79=1,"Bot resolves",IF(E79=2,"Bot triages, agent resolves","Immediate human handoff")) -> Bot resolves | G79: =IF(AND(E79=1,INDEX(Group_Summary!$J$6:$J$15,MATCH(B79,Group_Summary!$A$6:$A$15,0))="Pilot"),"Yes","No") -> No
A80: transfer_into_account | B80: Transfers | C80: =COUNTIF(Raw_Data!$B$2:$B$10004,"transfer_into_account") -> 113 | D80: =C80/SUM($C$5:$C$81) -> 0.011296611 | E80: 1 | F80: =IF(E80=1,"Bot resolves",IF(E80=2,"Bot triages, agent resolves","Immediate human handoff")) -> Bot resolves | G80: =IF(AND(E80=1,INDEX(Group_Summary!$J$6:$J$15,MATCH(B80,Group_Summary!$A$6:$A$15,0))="Pilot"),"Yes","No") -> No
A81: receiving_money | B81: Transfers | C81: =COUNTIF(Raw_Data!$B$2:$B$10004,"receiving_money") -> 95 | D81: =C81/SUM($C$5:$C$81) -> 0.0094971509 | E81: 1 | F81: =IF(E81=1,"Bot resolves",IF(E81=2,"Bot triages, agent resolves","Immediate human handoff")) -> Bot resolves | G81: =IF(AND(E81=1,INDEX(Group_Summary!$J$6:$J$15,MATCH(B81,Group_Summary!$A$6:$A$15,0))="Pilot"),"Yes","No") -> No
A82: Total | C82: =SUM(C5:C81) -> 10003 | D82: =SUM(D5:D81) -> 1

Sheet Group_Summary
A1: Business group summary and pilot selection
A2: Groups are ranked by bot-resolvable (risk 1) volume. The top N become the pilot; N is the blue input below.
A3: Groups in pilot (N): | B3: 4 | C3: Input: change to widen or narrow the pilot
A5: Business group | B5: Queries | C5: % of total | D5: Bot resolves (risk 1) | E5: Triage to agent (risk 2) | F5: Human only (risk 3) | G5: % bot-resolvable | H5: Intents | I5: Rank (by risk 1 vol.) | J5: Pilot?
A6: Card usage & features | B6: =SUMIFS(Intent_Analysis!$C$5:$C$81,Intent_Analysis!$B$5:$B$81,A6) -> 1491 | C6: =B6/SUM($B$6:$B$15) -> 0.14905528 | D6: =SUMIFS(Intent_Analysis!$C$5:$C$81,Intent_Analysis!$B$5:$B$81,$A6,Intent_Analysis!$E$5:$E$81,1) -> 1124 | E6: =SUMIFS(Intent_Analysis!$C$5:$C$81,Intent_Analysis!$B$5:$B$81,$A6,Intent_Analysis!$E$5:$E$81,2) -> 367 | F6: =SUMIFS(Intent_Analysis!$C$5:$C$81,Intent_Analysis!$B$5:$B$81,$A6,Intent_Analysis!$E$5:$E$81,3) -> 0 | G6: =IF(B6=0,0,D6/B6) -> 0.75385647 | H6: =COUNTIF(Intent_Analysis!$B$5:$B$81,A6) -> 15 | I6: =RANK(D6,$D$6:$D$15,0) -> 1 | J6: =IF(AND(I6<=$B$3,D6>0),"Pilot",IF(D6=0,"Not suited","Phase 2")) -> Pilot
A7: Card delivery & activation | B7: =SUMIFS(Intent_Analysis!$C$5:$C$81,Intent_Analysis!$B$5:$B$81,A7) -> 1047 | C7: =B7/SUM($B$6:$B$15) -> 0.1046686 | D7: =SUMIFS(Intent_Analysis!$C$5:$C$81,Intent_Analysis!$B$5:$B$81,$A7,Intent_Analysis!$E$5:$E$81,1) -> 1047 | E7: =SUMIFS(Intent_Analysis!$C$5:$C$81,Intent_Analysis!$B$5:$B$81,$A7,Intent_Analysis!$E$5:$E$81,2) -> 0 | F7: =SUMIFS(Intent_Analysis!$C$5:$C$81,Intent_Analysis!$B$5:$B$81,$A7,Intent_Analysis!$E$5:$E$81,3) -> 0 | G7: =IF(B7=0,0,D7/B7) -> 1 | H7: =COUNTIF(Intent_Analysis!$B$5:$B$81,A7) -> 8 | I7: =RANK(D7,$D$6:$D$15,0) -> 2 | J7: =IF(AND(I7<=$B$3,D7>0),"Pilot",IF(D7=0,"Not suited","Phase 2")) -> Pilot
A8: Fees & charges | B8: =SUMIFS(Intent_Analysis!$C$5:$C$81,Intent_Analysis!$B$5:$B$81,A8) -> 1048 | C8: =B8/SUM($B$6:$B$15) -> 0.10476857 | D8: =SUMIFS(Intent_Analysis!$C$5:$C$81,Intent_Analysis!$B$5:$B$81,$A8,Intent_Analysis!$E$5:$E$81,1) -> 882 | E8: =SUMIFS(Intent_Analysis!$C$5:$C$81,Intent_Analysis!$B$5:$B$81,$A8,Intent_Analysis!$E$5:$E$81,2) -> 166 | F8: =SUMIFS(Intent_Analysis!$C$5:$C$81,Intent_Analysis!$B$5:$B$81,$A8,Intent_Analysis!$E$5:$E$81,3) -> 0 | G8: =IF(B8=0,0,D8/B8) -> 0.84160305 | H8: =COUNTIF(Intent_Analysis!$B$5:$B$81,A8) -> 7 | I8: =RANK(D8,$D$6:$D$15,0) -> 3 | J8: =IF(AND(I8<=$B$3,D8>0),"Pilot",IF(D8=0,"Not suited","Phase 2")) -> Pilot
A9: Top-ups | B9: =SUMIFS(Intent_Analysis!$C$5:$C$81,Intent_Analysis!$B$5:$B$81,A9) -> 1007 | C9: =B9/SUM($B$6:$B$15) -> 0.1006698 | D9: =SUMIFS(Intent_Analysis!$C$5:$C$81,Intent_Analysis!$B$5:$B$81,$A9,Intent_Analysis!$E$5:$E$81,1) -> 567 | E9: =SUMIFS(Intent_Analysis!$C$5:$C$81,Intent_Analysis!$B$5:$B$81,$A9,Intent_Analysis!$E$5:$E$81,2) -> 440 | F9: =SUMIFS(Intent_Analysis!$C$5:$C$81,Intent_Analysis!$B$5:$B$81,$A9,Intent_Analysis!$E$5:$E$81,3) -> 0 | G9: =IF(B9=0,0,D9/B9) -> 0.56305859 | H9: =COUNTIF(Intent_Analysis!$B$5:$B$81,A9) -> 8 | I9: =RANK(D9,$D$6:$D$15,0) -> 4 | J9: =IF(AND(I9<=$B$3,D9>0),"Pilot",IF(D9=0,"Not suited","Phase 2")) -> Pilot
A10: Exchange rates & currencies | B10: =SUMIFS(Intent_Analysis!$C$5:$C$81,Intent_Analysis!$B$5:$B$81,A10) -> 815 | C10: =B10/SUM($B$6:$B$15) -> 0.081475557 | D10: =SUMIFS(Intent_Analysis!$C$5:$C$81,Intent_Analysis!$B$5:$B$81,$A10,Intent_Analysis!$E$5:$E$81,1) -> 485 | E10: =SUMIFS(Intent_Analysis!$C$5:$C$81,Intent_Analysis!$B$5:$B$81,$A10,Intent_Analysis!$E$5:$E$81,2) -> 330 | F10: =SUMIFS(Intent_Analysis!$C$5:$C$81,Intent_Analysis!$B$5:$B$81,$A10,Intent_Analysis!$E$5:$E$81,3) -> 0 | G10: =IF(B10=0,0,D10/B10) -> 0.59509202 | H10: =COUNTIF(Intent_Analysis!$B$5:$B$81,A10) -> 6 | I10: =RANK(D10,$D$6:$D$15,0) -> 5 | J10: =IF(AND(I10<=$B$3,D10>0),"Pilot",IF(D10=0,"Not suited","Phase 2")) -> Phase 2
A11: Account & identity | B11: =SUMIFS(Intent_Analysis!$C$5:$C$81,Intent_Analysis!$B$5:$B$81,A11) -> 884 | C11: =B11/SUM($B$6:$B$15) -> 0.088373488 | D11: =SUMIFS(Intent_Analysis!$C$5:$C$81,Intent_Analysis!$B$5:$B$81,$A11,Intent_Analysis!$E$5:$E$81,1) -> 448 | E11: =SUMIFS(Intent_Analysis!$C$5:$C$81,Intent_Analysis!$B$5:$B$81,$A11,Intent_Analysis!$E$5:$E$81,2) -> 328 | F11: =SUMIFS(Intent_Analysis!$C$5:$C$81,Intent_Analysis!$B$5:$B$81,$A11,Intent_Analysis!$E$5:$E$81,3) -> 108 | G11: =IF(B11=0,0,D11/B11) -> 0.50678733 | H11: =COUNTIF(Intent_Analysis!$B$5:$B$81,A11) -> 8 | I11: =RANK(D11,$D$6:$D$15,0) -> 6 | J11: =IF(AND(I11<=$B$3,D11>0),"Pilot",IF(D11=0,"Not suited","Phase 2")) -> Phase 2
A12: Transfers | B12: =SUMIFS(Intent_Analysis!$C$5:$C$81,Intent_Analysis!$B$5:$B$81,A12) -> 1409 | C12: =B12/SUM($B$6:$B$15) -> 0.14085774 | D12: =SUMIFS(Intent_Analysis!$C$5:$C$81,Intent_Analysis!$B$5:$B$81,$A12,Intent_Analysis!$E$5:$E$81,1) -> 336 | E12: =SUMIFS(Intent_Analysis!$C$5:$C$81,Intent_Analysis!$B$5:$B$81,$A12,Intent_Analysis!$E$5:$E$81,2) -> 1073 | F12: =SUMIFS(Intent_Analysis!$C$5:$C$81,Intent_Analysis!$B$5:$B$81,$A12,Intent_Analysis!$E$5:$E$81,3) -> 0 | G12: =IF(B12=0,0,D12/B12) -> 0.238467 | H12: =COUNTIF(Intent_Analysis!$B$5:$B$81,A12) -> 10 | I12: =RANK(D12,$D$6:$D$15,0) -> 7 | J12: =IF(AND(I12<=$B$3,D12>0),"Pilot",IF(D12=0,"Not suited","Phase 2")) -> Phase 2
A13: Cash, ATM & deposits | B13: =SUMIFS(Intent_Analysis!$C$5:$C$81,Intent_Analysis!$B$5:$B$81,A13) -> 677 | C13: =B13/SUM($B$6:$B$15) -> 0.067679696 | D13: =SUMIFS(Intent_Analysis!$C$5:$C$81,Intent_Analysis!$B$5:$B$81,$A13,Intent_Analysis!$E$5:$E$81,1) -> 0 | E13: =SUMIFS(Intent_Analysis!$C$5:$C$81,Intent_Analysis!$B$5:$B$81,$A13,Intent_Analysis!$E$5:$E$81,2) -> 497 | F13: =SUMIFS(Intent_Analysis!$C$5:$C$81,Intent_Analysis!$B$5:$B$81,$A13,Intent_Analysis!$E$5:$E$81,3) -> 180 | G13: =IF(B13=0,0,D13/B13) -> 0 | H13: =COUNTIF(Intent_Analysis!$B$5:$B$81,A13) -> 4 | I13: =RANK(D13,$D$6:$D$15,0) -> 8 | J13: =IF(AND(I13<=$B$3,D13>0),"Pilot",IF(D13=0,"Not suited","Phase 2")) -> Not suited
A14: Fraud & security | B14: =SUMIFS(Intent_Analysis!$C$5:$C$81,Intent_Analysis!$B$5:$B$81,A14) -> 799 | C14: =B14/SUM($B$6:$B$15) -> 0.079876037 | D14: =SUMIFS(Intent_Analysis!$C$5:$C$81,Intent_Analysis!$B$5:$B$81,$A14,Intent_Analysis!$E$5:$E$81,1) -> 0 | E14: =SUMIFS(Intent_Analysis!$C$5:$C$81,Intent_Analysis!$B$5:$B$81,$A14,Intent_Analysis!$E$5:$E$81,2) -> 0 | F14: =SUMIFS(Intent_Analysis!$C$5:$C$81,Intent_Analysis!$B$5:$B$81,$A14,Intent_Analysis!$E$5:$E$81,3) -> 799 | G14: =IF(B14=0,0,D14/B14) -> 0 | H14: =COUNTIF(Intent_Analysis!$B$5:$B$81,A14) -> 6 | I14: =RANK(D14,$D$6:$D$15,0) -> 8 | J14: =IF(AND(I14<=$B$3,D14>0),"Pilot",IF(D14=0,"Not suited","Phase 2")) -> Not suited
A15: Card payments & refunds | B15: =SUMIFS(Intent_Analysis!$C$5:$C$81,Intent_Analysis!$B$5:$B$81,A15) -> 826 | C15: =B15/SUM($B$6:$B$15) -> 0.082575227 | D15: =SUMIFS(Intent_Analysis!$C$5:$C$81,Intent_Analysis!$B$5:$B$81,$A15,Intent_Analysis!$E$5:$E$81,1) -> 0 | E15: =SUMIFS(Intent_Analysis!$C$5:$C$81,Intent_Analysis!$B$5:$B$81,$A15,Intent_Analysis!$E$5:$E$81,2) -> 482 | F15: =SUMIFS(Intent_Analysis!$C$5:$C$81,Intent_Analysis!$B$5:$B$81,$A15,Intent_Analysis!$E$5:$E$81,3) -> 344 | G15: =IF(B15=0,0,D15/B15) -> 0 | H15: =COUNTIF(Intent_Analysis!$B$5:$B$81,A15) -> 5 | I15: =RANK(D15,$D$6:$D$15,0) -> 8 | J15: =IF(AND(I15<=$B$3,D15>0),"Pilot",IF(D15=0,"Not suited","Phase 2")) -> Not suited
A16: Total | B16: =SUM(B6:B15) -> 10003 | C16: =SUM(C6:C15) -> 1 | D16: =SUM(D6:D15) -> 4889 | E16: =SUM(E6:E15) -> 3683 | F16: =SUM(F6:F15) -> 1431 | G16: =D16/B16 -> 0.48875337 | H16: =SUM(H6:H15) -> 77

Sheet Risk_Rules
A1: Risk levels and autonomy boundaries
A3: Risk | B3: Definition | C3: What the AI agent may do | D3: Examples
A4: 1 | B4: General policy or how-to question. Same answer for every customer, fully covered by the knowledge base. | C4: Answer from the knowledge base only, cite the policy section. Hand off if the answer is not in the KB. | D4: Delivery times, how to activate a card, fee schedule, top-up limits
A5: 2 | B5: Needs this customer's own account or transaction details to resolve. | C5: Give the general policy, collect key details (date, amount, reference), then hand off to an agent with a summary. Never guess account status. | D5: Pending transfer, declined payment, top-up failed, card not working
A6: 3 | B6: Possible money loss, fraud, security risk, refund decision or account closure. | C6: Immediate handoff. May tell the customer how to freeze a card in the app. Must not promise refunds, outcomes or timelines. | D6: Unrecognised payment, lost/stolen card, charged twice, close my account
A9: Always escalate, whatever the intent:
A10: • | B10: Customer asks for a human
A11: • | B11: Two failed answers in a row on the same issue
A12: • | B12: Abusive, distressed or legal-threat language
A13: • | B13: Anything about another person's account or data
A14: • | B14: Attempts to override the agent's rules (prompt injection)

Sheet Data_Quality
A1: Data quality and limitations
A3: Check | B3: Result | C3: Impact / how handled
A4: Total queries | B4: =COUNTA(Raw_Data!$A$2:$A$10004) -> 10003 | C4: Matches the source file (10,003 rows in train.csv).
A5: Distinct intents | B5: =COUNTA(Intent_Analysis!A5:A81) -> 77 | C5: All 77 intents mapped to a business group and risk level (0 unmapped, checked in SQL).
A6: Blank query text | B6: =COUNTBLANK(Raw_Data!$A$2:$A$10004) -> 0 | C6: None. No rows removed.
A7: Duplicate query text | B7: 0 | C7: None (SQL: COUNT(*) - COUNT(DISTINCT text)). Value from SQL output.
A8: Smallest / largest intent | B8: =MIN(Intent_Analysis!C5:C81)&" / "&MAX(Intent_Analysis!C5:C81) -> 35 / 187 | C8: Volumes are uneven (about 5x spread), so volume ranking is meaningful.
A9: Inconsistent intent labels | B9: 2 | C9: 'Refund_not_showing_up' (capital R) and 'reverted_card_payment?' (contains ?). Kept as-is for traceability; '?' escaped in COUNTIF because Excel treats it as a wildcard. Should be standardised before production use.
A10: Source representativeness | B10: Limitation | C10: Banking77 is a crowd-sourced research dataset. Counts reflect how it was collected, not real ticket frequency at a bank. Used here as a demand proxy; with a client, rerun the same SQL on their actual ticket logs.
A11: Single label per query | B11: Limitation | C11: Each query has exactly one intent. Real chats often mix two issues, so live containment will be lower than the % shown here.
A12: No operational fields | B12: Limitation | C12: No channel, priority, handle time or CSAT. Automation choice is based on volume and risk only; handle time should be added once client data is available.

Sheet SQL
A1: MySQL script used for this analysis (also in support_analysis.sql)
A3: -- =====================================================
A4: -- Banking support: which queries can an AI agent handle?
A5: -- MySQL 8.0+ | Data: Banking77 train.csv (PolyAI, CC BY 4.0)
A6: -- =====================================================
A7: USE support;
A9: -- 1. Raw data, loaded untouched
A10: DROP TABLE IF EXISTS queries;
A11: CREATE TABLE queries (
A12: text TEXT,
A13: category VARCHAR(100)
A14: );
... A165: WHERE rn <= 5;

Sheet Raw_Data
A1: Query text | B1: Intent | C1: Business group | D1: Risk
A2: I am still waiting on my card? | B2: card_arrival | C2: =INDEX(Intent_Analysis!$B$5:$B$81,MATCH(B2,Intent_Analysis!$A$5:$A$81,0)) -> Card delivery & activation | D2: =INDEX(Intent_Analysis!$E$5:$E$81,MATCH(B2,Intent_Analysis!$A$5:$A$81,0)) -> 1
A3: What can I do if my card still hasn't arrived after 2 weeks? | B3: card_arrival | C3: =INDEX(Intent_Analysis!$B$5:$B$81,MATCH(B3,Intent_Analysis!$A$5:$A$81,0)) -> Card delivery & activation | D3: =INDEX(Intent_Analysis!$E$5:$E$81,MATCH(B3,Intent_Analysis!$A$5:$A$81,0)) -> 1
A4: I have been waiting over a week. Is the card still coming? | B4: card_arrival | C4: =INDEX(Intent_Analysis!$B$5:$B$81,MATCH(B4,Intent_Analysis!$A$5:$A$81,0)) -> Card delivery & activation | D4: =INDEX(Intent_Analysis!$E$5:$E$81,MATCH(B4,Intent_Analysis!$A$5:$A$81,0)) -> 1
A5: Can I track my card while it is in the process of delivery? | B5: card_arrival | C5: =INDEX(Intent_Analysis!$B$5:$B$81,MATCH(B5,Intent_Analysis!$A$5:$A$81,0)) -> Card delivery & activation | D5: =INDEX(Intent_Analysis!$E$5:$E$81,MATCH(B5,Intent_Analysis!$A$5:$A$81,0)) -> 1
A6: How do I know if I will get my card, or if it is lost? | B6: card_arrival | C6: =INDEX(Intent_Analysis!$B$5:$B$81,MATCH(B6,Intent_Analysis!$A$5:$A$81,0)) -> Card delivery & activation | D6: =INDEX(Intent_Analysis!$E$5:$E$81,MATCH(B6,Intent_Analysis!$A$5:$A$81,0)) -> 1
A7: When did you send me my new card? | B7: card_arrival | C7: =INDEX(Intent_Analysis!$B$5:$B$81,MATCH(B7,Intent_Analysis!$A$5:$A$81,0)) -> Card delivery & activation | D7: =INDEX(Intent_Analysis!$E$5:$E$81,MATCH(B7,Intent_Analysis!$A$5:$A$81,0)) -> 1
A8: Do you have info about the card on delivery? | B8: card_arrival | C8: =INDEX(Intent_Analysis!$B$5:$B$81,MATCH(B8,Intent_Analysis!$A$5:$A$81,0)) -> Card delivery & activation | D8: =INDEX(Intent_Analysis!$E$5:$E$81,MATCH(B8,Intent_Analysis!$A$5:$A$81,0)) -> 1
A9: What do I do if I still have not received my new card? | B9: card_arrival | C9: =INDEX(Intent_Analysis!$B$5:$B$81,MATCH(B9,Intent_Analysis!$A$5:$A$81,0)) -> Card delivery & activation | D9: =INDEX(Intent_Analysis!$E$5:$E$81,MATCH(B9,Intent_Analysis!$A$5:$A$81,0)) -> 1
A10: Does the package with my card have tracking? | B10: card_arrival | C10: =INDEX(Intent_Analysis!$B$5:$B$81,MATCH(B10,Intent_Analysis!$A$5:$A$81,0)) -> Card delivery & activation | D10: =INDEX(Intent_Analysis!$E$5:$E$81,MATCH(B10,Intent_Analysis!$A$5:$A$81,0)) -> 1
A11: I ordered my card but it still isn't here | B11: card_arrival | C11: =INDEX(Intent_Analysis!$B$5:$B$81,MATCH(B11,Intent_Analysis!$A$5:$A$81,0)) -> Card delivery & activation | D11: =INDEX(Intent_Analysis!$E$5:$E$81,MATCH(B11,Intent_Analysis!$A$5:$A$81,0)) -> 1
A12: Why has my new card still not come? | B12: card_arrival | C12: =INDEX(Intent_Analysis!$B$5:$B$81,MATCH(B12,Intent_Analysis!$A$5:$A$81,0)) -> Card delivery & activation | D12: =INDEX(Intent_Analysis!$E$5:$E$81,MATCH(B12,Intent_Analysis!$A$5:$A$81,0)) -> 1
A13: I still haven't received my card after two weeks, is it lost? | B13: card_arrival | C13: =INDEX(Intent_Analysis!$B$5:$B$81,MATCH(B13,Intent_Analysis!$A$5:$A$81,0)) -> Card delivery & activation | D13: =INDEX(Intent_Analysis!$E$5:$E$81,MATCH(B13,Intent_Analysis!$A$5:$A$81,0)) -> 1
... A10004: Which countries are represented? | B10004: country_support | C10004: =INDEX(Intent_Analysis!$B$5:$B$81,MATCH(B10004,Intent_Analysis!$A$5:$A$81,0)) -> Exchange rates & currencies | D10004: =INDEX(Intent_Analysis!$E$5:$E$81,MATCH(B10004,Intent_Analysis!$A$5:$A$81,0)) -> 1
